hindilemmatizer/__init__.py
hindilemmatizer/lemmatizer.py
hindilemmatizer/data/data.csv
hindilemmatizer/data/direct.csv
hindilemmatizer/data/totalWords.txt
hindilemmatizer-0.5.6.dist-info/LICENSE
hindilemmatizer-0.5.6.dist-info/METADATA
hindilemmatizer-0.5.6.dist-info/WHEEL
hindilemmatizer-0.5.6.dist-info/top_level.txt
hindilemmatizer-0.5.6.dist-info/RECORD
