Metadata-Version: 2.1
Name: hindilemmatizer
Version: 0.5.6
Summary: A lemmatization package for hindi language, by students of MNIT Jaipur
Author: Nitish Bhardwaj
License-File: LICENSE
